.version
MANIFEST.in
README.rst
setup.cfg
setup.py
demo/basic.py
demo/beta.py
demo/demo1.py
demo/finite_radius.py
demo/floating_potential.py
demo/gui.py
demo/interp.py
demo/inverse_OML.py
demo/inverse_finite_radius.py
demo/inverse_lsq.py
demo/iri.py
demo/normalization.py
demo/normalization2.py
demo/profile.py
demo/profile2.py
langmuir/__init__.py
langmuir/analytical.py
langmuir/data.py
langmuir/finite_length.py
langmuir/finite_radius.py
langmuir/geometry.py
langmuir/iri.npz
langmuir/misc.py
langmuir/params.npz
langmuir/params_structured.npz
langmuir/species.py
langmuir/tables.py
langmuir/test_analytical.py
langmuir/test_finite_length.py
langmuir/test_finite_radius.py
langmuir/test_geometry.py
langmuir/test_interface.py
langmuir/test_misc.py
langmuir/test_species.py
langmuir/test_table.py
langmuir.egg-info/PKG-INFO
langmuir.egg-info/SOURCES.txt
langmuir.egg-info/dependency_links.txt
langmuir.egg-info/requires.txt
langmuir.egg-info/top_level.txt