Metadata-Version: 1.1
Name: langmuir
Version: 0.9.0
Summary: Functions for work on Langmuir probe theory
Home-page: https://github.com/langmuirproject/langmuir.git
Author: Sigvald Marholm
Author-email: marholm@marebakken.com
License: LGPL
Platform: UNKNOWN
Classifier: Programming Language :: Python :: 2.7
Classifier: Programming Language :: Python :: 3.5
Classifier: Programming Language :: Python :: 3.6
Classifier: Programming Language :: Python :: 3.7
Classifier: Programming Language :: Python :: 3.8
Classifier: Programming Language :: Python :: 3.9
